korcen/__init__.py
korcen/belittle.py
korcen/check.py
korcen/chinese.py
korcen/english.py
korcen/general.py
korcen/japanese.py
korcen/korcen.py
korcen/minor.py
korcen/parent.py
korcen/politics.py
korcen/race.py
korcen/sexual.py
korcen/special.py
korcen_test-0.0.4.dist-info/METADATA
korcen_test-0.0.4.dist-info/WHEEL
korcen_test-0.0.4.dist-info/top_level.txt
korcen_test-0.0.4.dist-info/RECORD
